crytapi/__init__.py
crytapi/base.py
crytapi/client.py
crytapi/client_async.py
crytapi/futures/__init__.py
crytapi/futures/fapi.py
crytapi/futures/order.py
crytapi/service/__init__.py
crytapi/service/api.py
crytapi/spot/__init__.py
crytapi/spot/order.py
crytapi/spot/sapi.py
crytapi-0.0.10.dist-info/METADATA
crytapi-0.0.10.dist-info/WHEEL
crytapi-0.0.10.dist-info/RECORD
